sphinxcontrib_platformpicker-1.4-nspkg.pth
sphinxcontrib/platformpicker.css
sphinxcontrib/platformpicker.js
sphinxcontrib/platformpicker.py
sphinxcontrib_platformpicker-1.4.dist-info/LICENSE.txt
sphinxcontrib_platformpicker-1.4.dist-info/METADATA
sphinxcontrib_platformpicker-1.4.dist-info/WHEEL
sphinxcontrib_platformpicker-1.4.dist-info/namespace_packages.txt
sphinxcontrib_platformpicker-1.4.dist-info/top_level.txt
sphinxcontrib_platformpicker-1.4.dist-info/RECORD
