Metadata-Version: 2.1
Name: sphinxcontrib-platformpicker
Version: 1.4
Summary: Platform picker extension for Sphinx
Author: whitequark
Author-email: whitequark@whitequark.org
License: MIT
Project-URL: Documentation, https://sphinxcontrib-platformpicker.readthedocs.io/
Project-URL: Source Code, https://github.com/whitequark/sphinxcontrib-platformpicker
Project-URL: Bug Tracker, https://github.com/whitequark/sphinxcontrib-platformpicker/issues
Classifier: Development Status :: 5 - Production/Stable
Classifier: Environment :: Console
Classifier: Environment :: Web Environment
Classifier: Intended Audience :: Developers
Classifier: License :: OSI Approved :: MIT License
Classifier: Operating System :: OS Independent
Classifier: Programming Language :: Python
Classifier: Topic :: Documentation
Classifier: Topic :: Utilities
License-File: LICENSE.txt
Requires-Dist: Sphinx (>=2.0)
